ecgai_data_physionet/__init__.py
ecgai_data_physionet/data/ptbxl_database.csv
ecgai_data_physionet/data/scp_statements.csv
ecgai_data_physionet/exceptions.py
ecgai_data_physionet/file_loader.py
ecgai_data_physionet/models/diagnostic_code.py
ecgai_data_physionet/models/ecg.py
ecgai_data_physionet/models/ecg_lead.py
ecgai_data_physionet/models/model_base.py
ecgai_data_physionet/physionet.py
ecgai_data_physionet/ptbxl.py
ecgai_data_physionet-0.1.25.dist-info/METADATA
ecgai_data_physionet-0.1.25.dist-info/WHEEL
ecgai_data_physionet-0.1.25.dist-info/RECORD
